Exhibition/__init__.py
Exhibition/ascii.py
Exhibition/color_palette.py
Exhibition/colors.py
Exhibition/image.py
Exhibition/sysinfo.py
xhibit-9.8.6.data/scripts/pos.sh
xhibit-9.8.6.data/scripts/shell.sh
xhibit-9.8.6.dist-info/LICENSE
xhibit-9.8.6.dist-info/METADATA
xhibit-9.8.6.dist-info/WHEEL
xhibit-9.8.6.dist-info/entry_points.txt
xhibit-9.8.6.dist-info/top_level.txt
xhibit-9.8.6.dist-info/RECORD
