Metadata-Version: 2.1
Name: xhibit
Version: 9.8.6
Summary: A python script to exhibit your ascii arts and sytem specs
Home-page: https://github.com/glowfi/xhibit
Author: glowfi
Classifier: Development Status :: 5 - Production/Stable
Classifier: Operating System :: POSIX :: Linux
Classifier: Intended Audience :: End Users/Desktop
Classifier: License :: OSI Approved :: GNU General Public License v3 or later (GPLv3+)
Classifier: Programming Language :: Python :: 3.9
Requires-Python: >=3.6
License-File: LICENSE
Requires-Dist: tcolorpy
Requires-Dist: importlib-metadata
